{"id":"38dd1c1e-8c4f-653e-f8b4-2b35100f62c2","name":"dynamodb-geo","timestamp":1390397965996,"requests":[{"collectionId":"38dd1c1e-8c4f-653e-f8b4-2b35100f62c2","id":"76e30278-b805-5636-c1a3-80bd00a05574","name":"describe-table","description":"","url":"172.18.169.204:8080","method":"POST","headers":"Accept-Encoding: identity\nX-Amz-Target: DynamoDB_20120810.DescribeTable\nHost: 172.18.169.204:8080\nX-Amz-Date: 20131227T115219Z\nContent-Type: application/x-amz-json-1.0\n","data":"{\n  \"TableName\": \"ilya_dynamo_geo_table5\"\n}","dataMode":"raw","timestamp":0,"responses":[],"version":2},{"collectionId":"38dd1c1e-8c4f-653e-f8b4-2b35100f62c2","id":"841ab6b9-47f4-657c-9a33-2e9eb8b6aabd","name":"query-rectangle","description":"","url":"http://localhost:8080/dynamodb-geo-server/dynamodb-geo","method":"POST","headers":"m: \nAccept-Encoding: identity\nX-Amz-Target: DynamoDB_20120810.GetItem\nHost: 172.18.169.204:8080\nX-Amz-Date: 20131227T115219Z\nContent-Type: application/x-amz-json-1.0\n","data":"{'action':'query-rectangle',\n 'request':{'minLat':47.286682,'minLng':-123.706970,'maxLat':48.734455,'maxLng':-100.965637}}\n","dataMode":"raw","timestamp":0,"responses":[],"version":2}]}
